abbreviation_extractor-0.1.4.dist-info/METADATA
abbreviation_extractor-0.1.4.dist-info/WHEEL
abbreviation_extractor-0.1.4.dist-info/licenses/LICENSE
abbreviation_extractor/__init__.py
abbreviation_extractor/__init__.pyi
abbreviation_extractor/py.typed
abbreviation_extractor/abbreviation_extractor.cpython-39-x86_64-linux-gnu.so
abbreviation_extractor-0.1.4.dist-info/RECORD
