Metadata-Version: 2.3
Name: abbreviation_extractor
Version: 0.1.4
Classifier: Programming Language :: Rust
Classifier: Programming Language :: Python :: Implementation :: CPython
Classifier: Programming Language :: Python :: Implementation :: PyPy
License-File: LICENSE
Summary: A library for extracting abbreviations from text.
Keywords: abbreviation,extraction,nlp,text-processing,biomedical
Author: Praise Oketola <oketola.praise@gmail.com>
Author-email: Praise Oketola <oketola.praise@gmail.com>
License: MIT
Requires-Python: >=3.8
Project-URL: Source Code, https://github.com/praise2112/abbreviation-extractor
